{"id":387213,"title":"【催眠NTR】JKお持ち帰り!性感帯感度20倍アップの催眠で失神寸前アヘ声&オホ声連続絶頂!【バイノーラル録音リアル体験】","circle_id":54631,"name":"うどん大好き100%","nsfw":true,"release":"2022-04-29","dl_count":2008,"price":924,"review_count":9,"rate_count":607,"rate_average_2dp":4.66,"rate_count_detail":[{"review_point":1,"count":1,"ratio":0},{"review_point":2,"count":7,"ratio":1},{"review_point":3,"count":44,"ratio":7},{"review_point":4,"count":96,"ratio":15},{"review_point":5,"count":459,"ratio":75}],"rank":[{"term":"month","category":"all","rank":97,"rank_date":"2022-05-28"},{"term":"month","category":"voice","rank":59,"rank_date":"2022-05-28"}],"has_subtitle":false,"create_date":"2022-05-06","vas":[{"id":"14cbdaae-7eb9-508f-829d-e3bda8097f00","name":"彩夢ひな"}],"tags":[{"id":70,"i18n":{"en-us":{"name":"Successive Orgasms"},"ja-jp":{"name":"連続絶頂"},"zh-cn":{"name":"连续高潮"}},"name":"连续高潮"},{"id":488,"i18n":{"en-us":{"name":"Oral Cumshot"},"ja-jp":{"name":"口内射精"},"zh-cn":{"name":"口爆"}},"name":"口爆"},{"id":302,"i18n":{"en-us":{"name":"Cuckoldry (Netori)"},"ja-jp":{"name":"寝取り"},"zh-cn":{"name":"寝取"}},"name":"寝取"},{"id":128,"i18n":{"en-us":{"name":"Internal Cumshot"},"ja-jp":{"name":"中出し"},"zh-cn":{"name":"内射/中出"}},"name":"内射/中出"},{"id":497,"i18n":{"en-us":{"name":"ASMR"},"ja-jp":{"name":"ASMR"},"zh-cn":{"name":"ASMR"}},"name":"ASMR"},{"id":400,"i18n":{"en-us":{"name":"Student"},"ja-jp":{"name":"学生"},"zh-cn":{"name":"学生"}},"name":"学生"},{"id":48,"i18n":{"en-us":{"name":"Cuckoldry (Netorare)"},"ja-jp":{"name":"寝取られ"},"zh-cn":{"name":"被寝取/NTR"}},"name":"被寝取/NTR"},{"id":157,"i18n":{"en-us":{"name":"Hypnosis"},"ja-jp":{"name":"催眠"},"zh-cn":{"name":"催眠"}},"name":"催眠"}],"circle":{"id":54631,"name":"うどん大好き100%"},"samCoverUrl":"https://api.asmr-200.com/api/cover/RJ387213.jpg?type=sam","thumbnailCoverUrl":"https://api.asmr-200.com/api/cover/RJ387213.jpg?type=240x240","mainCoverUrl":"https://api.asmr-200.com/api/cover/RJ387213.jpg?type=main"}