[{"type":"folder","title":"加工無し版","children":[{"type":"audio","hash":"1012984/1","title":"01.注意事項.wav","workTitle":"人妻寝取られ催眠 「奪われることで気持ち良くなってしまう惨めで弱いボク」","mediaStreamUrl":"https://raw.kiko-play-niptan.one/media/stream/daily/2023-02-06/RJ01012984/%E5%8A%A0%E5%B7%A5%E7%84%A1%E3%81%97%E7%89%88/01.%E6%B3%A8%E6%84%8F%E4%BA%8B%E9%A0%85.wav","mediaDownloadUrl":"https://raw.kiko-play-niptan.one/media/download/daily/2023-02-06/RJ01012984/%E5%8A%A0%E5%B7%A5%E7%84%A1%E3%81%97%E7%89%88/01.%E6%B3%A8%E6%84%8F%E4%BA%8B%E9%A0%85.wav","streamLowQualityUrl":"https://fast.kiko-play-niptan.one/media/stream/daily/2023-02-06/RJ01012984/%E5%8A%A0%E5%B7%A5%E7%84%A1%E3%81%97%E7%89%88/01.%E6%B3%A8%E6%84%8F%E4%BA%8B%E9%A0%85.m4a","duration":155.319812},{"type":"audio","hash":"1012984/3","title":"02-5.ちゃんとお留守番出来ているお利口さんへのメッセージ.wav","workTitle":"人妻寝取られ催眠 「奪われることで気持ち良くなってしまう惨めで弱いボク」","mediaStreamUrl":"https://raw.kiko-play-niptan.one/media/stream/daily/2023-02-06/RJ01012984/%E5%8A%A0%E5%B7%A5%E7%84%A1%E3%81%97%E7%89%88/02-5.%E3%81%A1%E3%82%83%E3%82%93%E3%81%A8%E3%81%8A%E7%95%99%E5%AE%88%E7%95%AA%E5%87%BA%E6%9D%A5%E3%81%A6%E3%81%84%E3%82%8B%E3%81%8A%E5%88%A9%E5%8F%A3%E3%81%95%E3%82%93%E3%81%B8%E3%81%AE%E3%83%A1%E3%83%83%E3%82%BB%E3%83%BC%E3%82%B8.wav","mediaDownloadUrl":"https://raw.kiko-play-niptan.one/media/download/daily/2023-02-06/RJ01012984/%E5%8A%A0%E5%B7%A5%E7%84%A1%E3%81%97%E7%89%88/02-5.%E3%81%A1%E3%82%83%E3%82%93%E3%81%A8%E3%81%8A%E7%95%99%E5%AE%88%E7%95%AA%E5%87%BA%E6%9D%A5%E3%81%A6%E3%81%84%E3%82%8B%E3%81%8A%E5%88%A9%E5%8F%A3%E3%81%95%E3%82%93%E3%81%B8%E3%81%AE%E3%83%A1%E3%83%83%E3%82%BB%E3%83%BC%E3%82%B8.wav","streamLowQualityUrl":"https://fast.kiko-play-niptan.one/media/stream/daily/2023-02-06/RJ01012984/%E5%8A%A0%E5%B7%A5%E7%84%A1%E3%81%97%E7%89%88/02-5.%E3%81%A1%E3%82%83%E3%82%93%E3%81%A8%E3%81%8A%E7%95%99%E5%AE%88%E7%95%AA%E5%87%BA%E6%9D%A5%E3%81%A6%E3%81%84%E3%82%8B%E3%81%8A%E5%88%A9%E5%8F%A3%E3%81%95%E3%82%93%E3%81%B8%E3%81%AE%E3%83%A1%E3%83%83%E3%82%BB%E3%83%BC%E3%82%B8.m4a","duration":421.0175},{"type":"audio","hash":"1012984/5","title":"02.寝取られ＝快感催眠洗脳.wav","workTitle":"人妻寝取られ催眠 「奪われることで気持ち良くなってしまう惨めで弱いボク」","mediaStreamUrl":"https://raw.kiko-play-niptan.one/media/stream/daily/2023-02-06/RJ01012984/%E5%8A%A0%E5%B7%A5%E7%84%A1%E3%81%97%E7%89%88/02.%E5%AF%9D%E5%8F%96%E3%82%89%E3%82%8C%EF%BC%9D%E5%BF%AB%E6%84%9F%E5%82%AC%E7%9C%A0%E6%B4%97%E8%84%B3.wav","mediaDownloadUrl":"https://raw.kiko-play-niptan.one/media/download/daily/2023-02-06/RJ01012984/%E5%8A%A0%E5%B7%A5%E7%84%A1%E3%81%97%E7%89%88/02.%E5%AF%9D%E5%8F%96%E3%82%89%E3%82%8C%EF%BC%9D%E5%BF%AB%E6%84%9F%E5%82%AC%E7%9C%A0%E6%B4%97%E8%84%B3.wav","streamLowQualityUrl":"https://fast.kiko-play-niptan.one/media/stream/daily/2023-02-06/RJ01012984/%E5%8A%A0%E5%B7%A5%E7%84%A1%E3%81%97%E7%89%88/02.%E5%AF%9D%E5%8F%96%E3%82%89%E3%82%8C%EF%BC%9D%E5%BF%AB%E6%84%9F%E5%82%AC%E7%9C%A0%E6%B4%97%E8%84%B3.m4a","duration":1454.098021},{"type":"audio","hash":"1012984/7","title":"03.寝取られ報告耳舐め囁き乳首責め手コキ.wav","workTitle":"人妻寝取られ催眠 「奪われることで気持ち良くなってしまう惨めで弱いボク」","mediaStreamUrl":"https://raw.kiko-play-niptan.one/media/stream/daily/2023-02-06/RJ01012984/%E5%8A%A0%E5%B7%A5%E7%84%A1%E3%81%97%E7%89%88/03.%E5%AF%9D%E5%8F%96%E3%82%89%E3%82%8C%E5%A0%B1%E5%91%8A%E8%80%B3%E8%88%90%E3%82%81%E5%9B%81%E3%81%8D%E4%B9%B3%E9%A6%96%E8%B2%AC%E3%82%81%E6%89%8B%E3%82%B3%E3%82%AD.wav","mediaDownloadUrl":"https://raw.kiko-play-niptan.one/media/download/daily/2023-02-06/RJ01012984/%E5%8A%A0%E5%B7%A5%E7%84%A1%E3%81%97%E7%89%88/03.%E5%AF%9D%E5%8F%96%E3%82%89%E3%82%8C%E5%A0%B1%E5%91%8A%E8%80%B3%E8%88%90%E3%82%81%E5%9B%81%E3%81%8D%E4%B9%B3%E9%A6%96%E8%B2%AC%E3%82%81%E6%89%8B%E3%82%B3%E3%82%AD.wav","streamLowQualityUrl":"https://fast.kiko-play-niptan.one/media/stream/daily/2023-02-06/RJ01012984/%E5%8A%A0%E5%B7%A5%E7%84%A1%E3%81%97%E7%89%88/03.%E5%AF%9D%E5%8F%96%E3%82%89%E3%82%8C%E5%A0%B1%E5%91%8A%E8%80%B3%E8%88%90%E3%82%81%E5%9B%81%E3%81%8D%E4%B9%B3%E9%A6%96%E8%B2%AC%E3%82%81%E6%89%8B%E3%82%B3%E3%82%AD.m4a","duration":1411.675271},{"type":"audio","hash":"1012984/9","title":"04.寝取られセックス実況＋オナニー誘導言葉責め通話.wav","workTitle":"人妻寝取られ催眠 「奪われることで気持ち良くなってしまう惨めで弱いボク」","mediaStreamUrl":"https://raw.kiko-play-niptan.one/media/stream/daily/2023-02-06/RJ01012984/%E5%8A%A0%E5%B7%A5%E7%84%A1%E3%81%97%E7%89%88/04.%E5%AF%9D%E5%8F%96%E3%82%89%E3%82%8C%E3%82%BB%E3%83%83%E3%82%AF%E3%82%B9%E5%AE%9F%E6%B3%81%EF%BC%8B%E3%82%AA%E3%83%8A%E3%83%8B%E3%83%BC%E8%AA%98%E5%B0%8E%E8%A8%80%E8%91%89%E8%B2%AC%E3%82%81%E9%80%9A%E8%A9%B1.wav","mediaDownloadUrl":"https://raw.kiko-play-niptan.one/media/download/daily/2023-02-06/RJ01012984/%E5%8A%A0%E5%B7%A5%E7%84%A1%E3%81%97%E7%89%88/04.%E5%AF%9D%E5%8F%96%E3%82%89%E3%82%8C%E3%82%BB%E3%83%83%E3%82%AF%E3%82%B9%E5%AE%9F%E6%B3%81%EF%BC%8B%E3%82%AA%E3%83%8A%E3%83%8B%E3%83%BC%E8%AA%98%E5%B0%8E%E8%A8%80%E8%91%89%E8%B2%AC%E3%82%81%E9%80%9A%E8%A9%B1.wav","streamLowQualityUrl":"https://fast.kiko-play-niptan.one/media/stream/daily/2023-02-06/RJ01012984/%E5%8A%A0%E5%B7%A5%E7%84%A1%E3%81%97%E7%89%88/04.%E5%AF%9D%E5%8F%96%E3%82%89%E3%82%8C%E3%82%BB%E3%83%83%E3%82%AF%E3%82%B9%E5%AE%9F%E6%B3%81%EF%BC%8B%E3%82%AA%E3%83%8A%E3%83%8B%E3%83%BC%E8%AA%98%E5%B0%8E%E8%A8%80%E8%91%89%E8%B2%AC%E3%82%81%E9%80%9A%E8%A9%B1.m4a","duration":976.311},{"type":"audio","hash":"1012984/11","title":"05.愛妻寝取られセックス鑑賞オナニー.wav","workTitle":"人妻寝取られ催眠 「奪われることで気持ち良くなってしまう惨めで弱いボク」","mediaStreamUrl":"https://raw.kiko-play-niptan.one/media/stream/daily/2023-02-06/RJ01012984/%E5%8A%A0%E5%B7%A5%E7%84%A1%E3%81%97%E7%89%88/05.%E6%84%9B%E5%A6%BB%E5%AF%9D%E5%8F%96%E3%82%89%E3%82%8C%E3%82%BB%E3%83%83%E3%82%AF%E3%82%B9%E9%91%91%E8%B3%9E%E3%82%AA%E3%83%8A%E3%83%8B%E3%83%BC.wav","mediaDownloadUrl":"https://raw.kiko-play-niptan.one/media/download/daily/2023-02-06/RJ01012984/%E5%8A%A0%E5%B7%A5%E7%84%A1%E3%81%97%E7%89%88/05.%E6%84%9B%E5%A6%BB%E5%AF%9D%E5%8F%96%E3%82%89%E3%82%8C%E3%82%BB%E3%83%83%E3%82%AF%E3%82%B9%E9%91%91%E8%B3%9E%E3%82%AA%E3%83%8A%E3%83%8B%E3%83%BC.wav","streamLowQualityUrl":"https://fast.kiko-play-niptan.one/media/stream/daily/2023-02-06/RJ01012984/%E5%8A%A0%E5%B7%A5%E7%84%A1%E3%81%97%E7%89%88/05.%E6%84%9B%E5%A6%BB%E5%AF%9D%E5%8F%96%E3%82%89%E3%82%8C%E3%82%BB%E3%83%83%E3%82%AF%E3%82%B9%E9%91%91%E8%B3%9E%E3%82%AA%E3%83%8A%E3%83%8B%E3%83%BC.m4a","duration":964.681},{"type":"audio","hash":"1012984/13","title":"06.催眠解除.wav","workTitle":"人妻寝取られ催眠 「奪われることで気持ち良くなってしまう惨めで弱いボク」","mediaStreamUrl":"https://raw.kiko-play-niptan.one/media/stream/daily/2023-02-06/RJ01012984/%E5%8A%A0%E5%B7%A5%E7%84%A1%E3%81%97%E7%89%88/06.%E5%82%AC%E7%9C%A0%E8%A7%A3%E9%99%A4.wav","mediaDownloadUrl":"https://raw.kiko-play-niptan.one/media/download/daily/2023-02-06/RJ01012984/%E5%8A%A0%E5%B7%A5%E7%84%A1%E3%81%97%E7%89%88/06.%E5%82%AC%E7%9C%A0%E8%A7%A3%E9%99%A4.wav","streamLowQualityUrl":"https://fast.kiko-play-niptan.one/media/stream/daily/2023-02-06/RJ01012984/%E5%8A%A0%E5%B7%A5%E7%84%A1%E3%81%97%E7%89%88/06.%E5%82%AC%E7%9C%A0%E8%A7%A3%E9%99%A4.m4a","duration":339.845}]},{"type":"folder","title":"おまけ","children":[{"type":"audio","hash":"1012984/15","title":"あまりの可憐さにエンドレステイク2.wav","workTitle":"人妻寝取られ催眠 「奪われることで気持ち良くなってしまう惨めで弱いボク」","mediaStreamUrl":"https://raw.kiko-play-niptan.one/media/stream/daily/2023-02-06/RJ01012984/%E3%81%8A%E3%81%BE%E3%81%91/%E3%81%82%E3%81%BE%E3%82%8A%E3%81%AE%E5%8F%AF%E6%86%90%E3%81%95%E3%81%AB%E3%82%A8%E3%83%B3%E3%83%89%E3%83%AC%E3%82%B9%E3%83%86%E3%82%A4%E3%82%AF2.wav","mediaDownloadUrl":"https://raw.kiko-play-niptan.one/media/download/daily/2023-02-06/RJ01012984/%E3%81%8A%E3%81%BE%E3%81%91/%E3%81%82%E3%81%BE%E3%82%8A%E3%81%AE%E5%8F%AF%E6%86%90%E3%81%95%E3%81%AB%E3%82%A8%E3%83%B3%E3%83%89%E3%83%AC%E3%82%B9%E3%83%86%E3%82%A4%E3%82%AF2.wav","streamLowQualityUrl":"https://fast.kiko-play-niptan.one/media/stream/daily/2023-02-06/RJ01012984/%E3%81%8A%E3%81%BE%E3%81%91/%E3%81%82%E3%81%BE%E3%82%8A%E3%81%AE%E5%8F%AF%E6%86%90%E3%81%95%E3%81%AB%E3%82%A8%E3%83%B3%E3%83%89%E3%83%AC%E3%82%B9%E3%83%86%E3%82%A4%E3%82%AF2.m4a","duration":15.784036},{"type":"image","hash":"1012984/16","title":"寝取られ人妻表紙.jpg","workTitle":"人妻寝取られ催眠 「奪われることで気持ち良くなってしまう惨めで弱いボク」","mediaStreamUrl":"https://raw.kiko-play-niptan.one/media/stream/daily/2023-02-06/RJ01012984/%E3%81%8A%E3%81%BE%E3%81%91/%E5%AF%9D%E5%8F%96%E3%82%89%E3%82%8C%E4%BA%BA%E5%A6%BB%E8%A1%A8%E7%B4%99.jpg","mediaDownloadUrl":"https://raw.kiko-play-niptan.one/media/download/daily/2023-02-06/RJ01012984/%E3%81%8A%E3%81%BE%E3%81%91/%E5%AF%9D%E5%8F%96%E3%82%89%E3%82%8C%E4%BA%BA%E5%A6%BB%E8%A1%A8%E7%B4%99.jpg"},{"type":"image","hash":"1012984/18","title":"表紙ラフ.jpg","workTitle":"人妻寝取られ催眠 「奪われることで気持ち良くなってしまう惨めで弱いボク」","mediaStreamUrl":"https://raw.kiko-play-niptan.one/media/stream/daily/2023-02-06/RJ01012984/%E3%81%8A%E3%81%BE%E3%81%91/%E8%A1%A8%E7%B4%99%E3%83%A9%E3%83%95.jpg","mediaDownloadUrl":"https://raw.kiko-play-niptan.one/media/download/daily/2023-02-06/RJ01012984/%E3%81%8A%E3%81%BE%E3%81%91/%E8%A1%A8%E7%B4%99%E3%83%A9%E3%83%95.jpg"},{"type":"audio","hash":"1012984/19","title":"野上菜月様　本編用フリートーク.wav","workTitle":"人妻寝取られ催眠 「奪われることで気持ち良くなってしまう惨めで弱いボク」","mediaStreamUrl":"https://raw.kiko-play-niptan.one/media/stream/daily/2023-02-06/RJ01012984/%E3%81%8A%E3%81%BE%E3%81%91/%E9%87%8E%E4%B8%8A%E8%8F%9C%E6%9C%88%E6%A7%98%E3%80%80%E6%9C%AC%E7%B7%A8%E7%94%A8%E3%83%95%E3%83%AA%E3%83%BC%E3%83%88%E3%83%BC%E3%82%AF.wav","mediaDownloadUrl":"https://raw.kiko-play-niptan.one/media/download/daily/2023-02-06/RJ01012984/%E3%81%8A%E3%81%BE%E3%81%91/%E9%87%8E%E4%B8%8A%E8%8F%9C%E6%9C%88%E6%A7%98%E3%80%80%E6%9C%AC%E7%B7%A8%E7%94%A8%E3%83%95%E3%83%AA%E3%83%BC%E3%83%88%E3%83%BC%E3%82%AF.wav","streamLowQualityUrl":"https://fast.kiko-play-niptan.one/media/stream/daily/2023-02-06/RJ01012984/%E3%81%8A%E3%81%BE%E3%81%91/%E9%87%8E%E4%B8%8A%E8%8F%9C%E6%9C%88%E6%A7%98%E3%80%80%E6%9C%AC%E7%B7%A8%E7%94%A8%E3%83%95%E3%83%AA%E3%83%BC%E3%83%88%E3%83%BC%E3%82%AF.m4a","duration":273.064375}]},{"type":"audio","hash":"1012984/0","title":"01.注意事項.wav","workTitle":"人妻寝取られ催眠 「奪われることで気持ち良くなってしまう惨めで弱いボク」","mediaStreamUrl":"https://raw.kiko-play-niptan.one/media/stream/daily/2023-02-06/RJ01012984/01.%E6%B3%A8%E6%84%8F%E4%BA%8B%E9%A0%85.wav","mediaDownloadUrl":"https://raw.kiko-play-niptan.one/media/download/daily/2023-02-06/RJ01012984/01.%E6%B3%A8%E6%84%8F%E4%BA%8B%E9%A0%85.wav","streamLowQualityUrl":"https://fast.kiko-play-niptan.one/media/stream/daily/2023-02-06/RJ01012984/01.%E6%B3%A8%E6%84%8F%E4%BA%8B%E9%A0%85.m4a","duration":155.319812},{"type":"audio","hash":"1012984/2","title":"02-5.ちゃんとお留守番出来ているお利口さんへのメッセージ.wav","workTitle":"人妻寝取られ催眠 「奪われることで気持ち良くなってしまう惨めで弱いボク」","mediaStreamUrl":"https://raw.kiko-play-niptan.one/media/stream/daily/2023-02-06/RJ01012984/02-5.%E3%81%A1%E3%82%83%E3%82%93%E3%81%A8%E3%81%8A%E7%95%99%E5%AE%88%E7%95%AA%E5%87%BA%E6%9D%A5%E3%81%A6%E3%81%84%E3%82%8B%E3%81%8A%E5%88%A9%E5%8F%A3%E3%81%95%E3%82%93%E3%81%B8%E3%81%AE%E3%83%A1%E3%83%83%E3%82%BB%E3%83%BC%E3%82%B8.wav","mediaDownloadUrl":"https://raw.kiko-play-niptan.one/media/download/daily/2023-02-06/RJ01012984/02-5.%E3%81%A1%E3%82%83%E3%82%93%E3%81%A8%E3%81%8A%E7%95%99%E5%AE%88%E7%95%AA%E5%87%BA%E6%9D%A5%E3%81%A6%E3%81%84%E3%82%8B%E3%81%8A%E5%88%A9%E5%8F%A3%E3%81%95%E3%82%93%E3%81%B8%E3%81%AE%E3%83%A1%E3%83%83%E3%82%BB%E3%83%BC%E3%82%B8.wav","streamLowQualityUrl":"https://fast.kiko-play-niptan.one/media/stream/daily/2023-02-06/RJ01012984/02-5.%E3%81%A1%E3%82%83%E3%82%93%E3%81%A8%E3%81%8A%E7%95%99%E5%AE%88%E7%95%AA%E5%87%BA%E6%9D%A5%E3%81%A6%E3%81%84%E3%82%8B%E3%81%8A%E5%88%A9%E5%8F%A3%E3%81%95%E3%82%93%E3%81%B8%E3%81%AE%E3%83%A1%E3%83%83%E3%82%BB%E3%83%BC%E3%82%B8.m4a","duration":420.83975},{"type":"audio","hash":"1012984/4","title":"02.寝取られ＝快感催眠洗脳.wav","workTitle":"人妻寝取られ催眠 「奪われることで気持ち良くなってしまう惨めで弱いボク」","mediaStreamUrl":"https://raw.kiko-play-niptan.one/media/stream/daily/2023-02-06/RJ01012984/02.%E5%AF%9D%E5%8F%96%E3%82%89%E3%82%8C%EF%BC%9D%E5%BF%AB%E6%84%9F%E5%82%AC%E7%9C%A0%E6%B4%97%E8%84%B3.wav","mediaDownloadUrl":"https://raw.kiko-play-niptan.one/media/download/daily/2023-02-06/RJ01012984/02.%E5%AF%9D%E5%8F%96%E3%82%89%E3%82%8C%EF%BC%9D%E5%BF%AB%E6%84%9F%E5%82%AC%E7%9C%A0%E6%B4%97%E8%84%B3.wav","streamLowQualityUrl":"https://fast.kiko-play-niptan.one/media/stream/daily/2023-02-06/RJ01012984/02.%E5%AF%9D%E5%8F%96%E3%82%89%E3%82%8C%EF%BC%9D%E5%BF%AB%E6%84%9F%E5%82%AC%E7%9C%A0%E6%B4%97%E8%84%B3.m4a","duration":1454.098021},{"type":"audio","hash":"1012984/6","title":"03.寝取られ報告耳舐め囁き乳首責め手コキ.wav","workTitle":"人妻寝取られ催眠 「奪われることで気持ち良くなってしまう惨めで弱いボク」","mediaStreamUrl":"https://raw.kiko-play-niptan.one/media/stream/daily/2023-02-06/RJ01012984/03.%E5%AF%9D%E5%8F%96%E3%82%89%E3%82%8C%E5%A0%B1%E5%91%8A%E8%80%B3%E8%88%90%E3%82%81%E5%9B%81%E3%81%8D%E4%B9%B3%E9%A6%96%E8%B2%AC%E3%82%81%E6%89%8B%E3%82%B3%E3%82%AD.wav","mediaDownloadUrl":"https://raw.kiko-play-niptan.one/media/download/daily/2023-02-06/RJ01012984/03.%E5%AF%9D%E5%8F%96%E3%82%89%E3%82%8C%E5%A0%B1%E5%91%8A%E8%80%B3%E8%88%90%E3%82%81%E5%9B%81%E3%81%8D%E4%B9%B3%E9%A6%96%E8%B2%AC%E3%82%81%E6%89%8B%E3%82%B3%E3%82%AD.wav","streamLowQualityUrl":"https://fast.kiko-play-niptan.one/media/stream/daily/2023-02-06/RJ01012984/03.%E5%AF%9D%E5%8F%96%E3%82%89%E3%82%8C%E5%A0%B1%E5%91%8A%E8%80%B3%E8%88%90%E3%82%81%E5%9B%81%E3%81%8D%E4%B9%B3%E9%A6%96%E8%B2%AC%E3%82%81%E6%89%8B%E3%82%B3%E3%82%AD.m4a","duration":1411.675271},{"type":"audio","hash":"1012984/8","title":"04.寝取られセックス実況＋オナニー誘導言葉責め通話.wav","workTitle":"人妻寝取られ催眠 「奪われることで気持ち良くなってしまう惨めで弱いボク」","mediaStreamUrl":"https://raw.kiko-play-niptan.one/media/stream/daily/2023-02-06/RJ01012984/04.%E5%AF%9D%E5%8F%96%E3%82%89%E3%82%8C%E3%82%BB%E3%83%83%E3%82%AF%E3%82%B9%E5%AE%9F%E6%B3%81%EF%BC%8B%E3%82%AA%E3%83%8A%E3%83%8B%E3%83%BC%E8%AA%98%E5%B0%8E%E8%A8%80%E8%91%89%E8%B2%AC%E3%82%81%E9%80%9A%E8%A9%B1.wav","mediaDownloadUrl":"https://raw.kiko-play-niptan.one/media/download/daily/2023-02-06/RJ01012984/04.%E5%AF%9D%E5%8F%96%E3%82%89%E3%82%8C%E3%82%BB%E3%83%83%E3%82%AF%E3%82%B9%E5%AE%9F%E6%B3%81%EF%BC%8B%E3%82%AA%E3%83%8A%E3%83%8B%E3%83%BC%E8%AA%98%E5%B0%8E%E8%A8%80%E8%91%89%E8%B2%AC%E3%82%81%E9%80%9A%E8%A9%B1.wav","streamLowQualityUrl":"https://fast.kiko-play-niptan.one/media/stream/daily/2023-02-06/RJ01012984/04.%E5%AF%9D%E5%8F%96%E3%82%89%E3%82%8C%E3%82%BB%E3%83%83%E3%82%AF%E3%82%B9%E5%AE%9F%E6%B3%81%EF%BC%8B%E3%82%AA%E3%83%8A%E3%83%8B%E3%83%BC%E8%AA%98%E5%B0%8E%E8%A8%80%E8%91%89%E8%B2%AC%E3%82%81%E9%80%9A%E8%A9%B1.m4a","duration":979.976687},{"type":"audio","hash":"1012984/10","title":"05.愛妻寝取られセックス鑑賞オナニー.wav","workTitle":"人妻寝取られ催眠 「奪われることで気持ち良くなってしまう惨めで弱いボク」","mediaStreamUrl":"https://raw.kiko-play-niptan.one/media/stream/daily/2023-02-06/RJ01012984/05.%E6%84%9B%E5%A6%BB%E5%AF%9D%E5%8F%96%E3%82%89%E3%82%8C%E3%82%BB%E3%83%83%E3%82%AF%E3%82%B9%E9%91%91%E8%B3%9E%E3%82%AA%E3%83%8A%E3%83%8B%E3%83%BC.wav","mediaDownloadUrl":"https://raw.kiko-play-niptan.one/media/download/daily/2023-02-06/RJ01012984/05.%E6%84%9B%E5%A6%BB%E5%AF%9D%E5%8F%96%E3%82%89%E3%82%8C%E3%82%BB%E3%83%83%E3%82%AF%E3%82%B9%E9%91%91%E8%B3%9E%E3%82%AA%E3%83%8A%E3%83%8B%E3%83%BC.wav","streamLowQualityUrl":"https://fast.kiko-play-niptan.one/media/stream/daily/2023-02-06/RJ01012984/05.%E6%84%9B%E5%A6%BB%E5%AF%9D%E5%8F%96%E3%82%89%E3%82%8C%E3%82%BB%E3%83%83%E3%82%AF%E3%82%B9%E9%91%91%E8%B3%9E%E3%82%AA%E3%83%8A%E3%83%8B%E3%83%BC.m4a","duration":976.622104},{"type":"audio","hash":"1012984/12","title":"06.催眠解除.wav","workTitle":"人妻寝取られ催眠 「奪われることで気持ち良くなってしまう惨めで弱いボク」","mediaStreamUrl":"https://raw.kiko-play-niptan.one/media/stream/daily/2023-02-06/RJ01012984/06.%E5%82%AC%E7%9C%A0%E8%A7%A3%E9%99%A4.wav","mediaDownloadUrl":"https://raw.kiko-play-niptan.one/media/download/daily/2023-02-06/RJ01012984/06.%E5%82%AC%E7%9C%A0%E8%A7%A3%E9%99%A4.wav","streamLowQualityUrl":"https://fast.kiko-play-niptan.one/media/stream/daily/2023-02-06/RJ01012984/06.%E5%82%AC%E7%9C%A0%E8%A7%A3%E9%99%A4.m4a","duration":339.845},{"type":"other","hash":"1012984/14","title":"【寝取催眠】　脚本　.pdf","workTitle":"人妻寝取られ催眠 「奪われることで気持ち良くなってしまう惨めで弱いボク」","mediaStreamUrl":"https://raw.kiko-play-niptan.one/media/stream/daily/2023-02-06/RJ01012984/%E3%80%90%E5%AF%9D%E5%8F%96%E5%82%AC%E7%9C%A0%E3%80%91%E3%80%80%E8%84%9A%E6%9C%AC%E3%80%80.pdf","mediaDownloadUrl":"https://raw.kiko-play-niptan.one/media/download/daily/2023-02-06/RJ01012984/%E3%80%90%E5%AF%9D%E5%8F%96%E5%82%AC%E7%9C%A0%E3%80%91%E3%80%80%E8%84%9A%E6%9C%AC%E3%80%80.pdf"},{"type":"text","hash":"1012984/17","title":"本作をお買い上げ頂いたあなたへ.txt","workTitle":"人妻寝取られ催眠 「奪われることで気持ち良くなってしまう惨めで弱いボク」","mediaStreamUrl":"https://api.asmr-200.com/api/media/stream/1012984/17","mediaDownloadUrl":"https://raw.kiko-play-niptan.one/media/download/daily/2023-02-06/RJ01012984/%E6%9C%AC%E4%BD%9C%E3%82%92%E3%81%8A%E8%B2%B7%E3%81%84%E4%B8%8A%E3%81%92%E9%A0%82%E3%81%84%E3%81%9F%E3%81%82%E3%81%AA%E3%81%9F%E3%81%B8.txt"}]