{"id":344381,"title":"逆痴漢してきた変態JKを巨根チンポで分からせる満員電車SEX","circle_id":56901,"name":"Rの消失","nsfw":true,"release":"2021-10-12","dl_count":1661,"price":385,"review_count":9,"rate_count":477,"rate_average_2dp":4.62,"rate_count_detail":[{"review_point":1,"count":2,"ratio":0},{"review_point":2,"count":3,"ratio":0},{"review_point":3,"count":43,"ratio":9},{"review_point":4,"count":80,"ratio":16},{"review_point":5,"count":349,"ratio":73}],"rank":null,"has_subtitle":false,"create_date":"2022-01-16","vas":[{"id":"b21301e3-fae7-5748-8044-9cee3684b433","name":"栗生ひなた"}],"tags":[{"id":400,"i18n":{"en-us":{"name":"Student"},"ja-jp":{"name":"学生"},"zh-cn":{"name":"学生"}},"name":"学生"},{"id":415,"i18n":{"en-us":{"name":"Gal"},"ja-jp":{"name":"ギャル"},"zh-cn":{"name":"辣妹"}},"name":"辣妹"},{"id":138,"i18n":{"en-us":{"name":"Blowjob / Fellatio"},"ja-jp":{"name":"フェラチオ"},"zh-cn":{"name":"口交"}},"name":"口交"},{"id":139,"i18n":{"en-us":{"name":"Molestation"},"ja-jp":{"name":"痴漢"},"zh-cn":{"name":"痴汉"}},"name":"痴汉"},{"id":113,"i18n":{"en-us":{"name":"Rape"},"ja-jp":{"name":"レイプ"},"zh-cn":{"name":"强奸"}},"name":"强奸"},{"id":115,"i18n":{"en-us":{"name":"Reverse Rape"},"ja-jp":{"name":"逆レイプ"},"zh-cn":{"name":"逆强奸/女上男"}},"name":"逆强奸/女上男"},{"id":301,"i18n":{"en-us":{"name":"Train"},"ja-jp":{"name":"電車"},"zh-cn":{"name":"电车"}},"name":"电车"},{"id":128,"i18n":{"en-us":{"name":"Internal Cumshot"},"ja-jp":{"name":"中出し"},"zh-cn":{"name":"内射/中出"}},"name":"内射/中出"}],"circle":{"id":56901,"name":"Rの消失"},"samCoverUrl":"https://api.asmr-200.com/api/cover/RJ344381.jpg?type=sam","thumbnailCoverUrl":"https://api.asmr-200.com/api/cover/RJ344381.jpg?type=240x240","mainCoverUrl":"https://api.asmr-200.com/api/cover/RJ344381.jpg?type=main"}