[{"type":"audio","hash":"253818/0","title":"01_１日目.mp3","workTitle":"ヤンデレ花嫁とのいちゃらぶ監禁生活","mediaStreamUrl":"https://raw.kiko-play-niptan.one/media/stream/hvdb/6000-6099/RJ253818/01_%EF%BC%91%E6%97%A5%E7%9B%AE.mp3","mediaDownloadUrl":"https://raw.kiko-play-niptan.one/media/download/hvdb/6000-6099/RJ253818/01_%EF%BC%91%E6%97%A5%E7%9B%AE.mp3","streamLowQualityUrl":"","duration":231.262042},{"type":"audio","hash":"253818/1","title":"02_２日目.mp3","workTitle":"ヤンデレ花嫁とのいちゃらぶ監禁生活","mediaStreamUrl":"https://raw.kiko-play-niptan.one/media/stream/hvdb/6000-6099/RJ253818/02_%EF%BC%92%E6%97%A5%E7%9B%AE.mp3","mediaDownloadUrl":"https://raw.kiko-play-niptan.one/media/download/hvdb/6000-6099/RJ253818/02_%EF%BC%92%E6%97%A5%E7%9B%AE.mp3","streamLowQualityUrl":"","duration":143.882417},{"type":"audio","hash":"253818/2","title":"03_３日目.mp3","workTitle":"ヤンデレ花嫁とのいちゃらぶ監禁生活","mediaStreamUrl":"https://raw.kiko-play-niptan.one/media/stream/hvdb/6000-6099/RJ253818/03_%EF%BC%93%E6%97%A5%E7%9B%AE.mp3","mediaDownloadUrl":"https://raw.kiko-play-niptan.one/media/download/hvdb/6000-6099/RJ253818/03_%EF%BC%93%E6%97%A5%E7%9B%AE.mp3","streamLowQualityUrl":"","duration":240.953458},{"type":"audio","hash":"253818/3","title":"04_７日目.mp3","workTitle":"ヤンデレ花嫁とのいちゃらぶ監禁生活","mediaStreamUrl":"https://raw.kiko-play-niptan.one/media/stream/hvdb/6000-6099/RJ253818/04_%EF%BC%97%E6%97%A5%E7%9B%AE.mp3","mediaDownloadUrl":"https://raw.kiko-play-niptan.one/media/download/hvdb/6000-6099/RJ253818/04_%EF%BC%97%E6%97%A5%E7%9B%AE.mp3","streamLowQualityUrl":"","duration":560.613875},{"type":"audio","hash":"253818/4","title":"05_いつかの.mp3","workTitle":"ヤンデレ花嫁とのいちゃらぶ監禁生活","mediaStreamUrl":"https://raw.kiko-play-niptan.one/media/stream/hvdb/6000-6099/RJ253818/05_%E3%81%84%E3%81%A4%E3%81%8B%E3%81%AE.mp3","mediaDownloadUrl":"https://raw.kiko-play-niptan.one/media/download/hvdb/6000-6099/RJ253818/05_%E3%81%84%E3%81%A4%E3%81%8B%E3%81%AE.mp3","streamLowQualityUrl":"","duration":416.365708},{"type":"image","hash":"253818/5","title":"hanayome.jpg","workTitle":"ヤンデレ花嫁とのいちゃらぶ監禁生活","mediaStreamUrl":"https://raw.kiko-play-niptan.one/media/stream/hvdb/6000-6099/RJ253818/hanayome.jpg","mediaDownloadUrl":"https://raw.kiko-play-niptan.one/media/download/hvdb/6000-6099/RJ253818/hanayome.jpg"},{"type":"image","hash":"253818/6","title":"hanayomepn.png","workTitle":"ヤンデレ花嫁とのいちゃらぶ監禁生活","mediaStreamUrl":"https://raw.kiko-play-niptan.one/media/stream/hvdb/6000-6099/RJ253818/hanayomepn.png","mediaDownloadUrl":"https://raw.kiko-play-niptan.one/media/download/hvdb/6000-6099/RJ253818/hanayomepn.png"},{"type":"image","hash":"253818/7","title":"ikonhanayome.jpg","workTitle":"ヤンデレ花嫁とのいちゃらぶ監禁生活","mediaStreamUrl":"https://raw.kiko-play-niptan.one/media/stream/hvdb/6000-6099/RJ253818/ikonhanayome.jpg","mediaDownloadUrl":"https://raw.kiko-play-niptan.one/media/download/hvdb/6000-6099/RJ253818/ikonhanayome.jpg"}]