[{"type":"folder","title":"2.MP3版","children":[{"type":"audio","hash":"418548/0","title":"0.プロローグ .mp3","workTitle":"【逆レイプ】【オホ声】【連続射精】マッドナースの搾精実験〜敵組織の悪のナースに捕まった貴方は一日中連続搾精で快楽実験のモルモットにされる〜","mediaStreamUrl":"https://raw.kiko-play-niptan.one/media/stream/daily/2022-10-15/RJ418548/2.MP3%E7%89%88/0.%E3%83%97%E3%83%AD%E3%83%AD%E3%83%BC%E3%82%B0%20.mp3","mediaDownloadUrl":"https://raw.kiko-play-niptan.one/media/download/daily/2022-10-15/RJ418548/2.MP3%E7%89%88/0.%E3%83%97%E3%83%AD%E3%83%AD%E3%83%BC%E3%82%B0%20.mp3","streamLowQualityUrl":"","duration":343.379625},{"type":"audio","hash":"418548/4","title":"1.第1章 .mp3","workTitle":"【逆レイプ】【オホ声】【連続射精】マッドナースの搾精実験〜敵組織の悪のナースに捕まった貴方は一日中連続搾精で快楽実験のモルモットにされる〜","mediaStreamUrl":"https://raw.kiko-play-niptan.one/media/stream/daily/2022-10-15/RJ418548/2.MP3%E7%89%88/1.%E7%AC%AC1%E7%AB%A0%20.mp3","mediaDownloadUrl":"https://raw.kiko-play-niptan.one/media/download/daily/2022-10-15/RJ418548/2.MP3%E7%89%88/1.%E7%AC%AC1%E7%AB%A0%20.mp3","streamLowQualityUrl":"","duration":1158.791875},{"type":"audio","hash":"418548/8","title":"2.第2章 .mp3","workTitle":"【逆レイプ】【オホ声】【連続射精】マッドナースの搾精実験〜敵組織の悪のナースに捕まった貴方は一日中連続搾精で快楽実験のモルモットにされる〜","mediaStreamUrl":"https://raw.kiko-play-niptan.one/media/stream/daily/2022-10-15/RJ418548/2.MP3%E7%89%88/2.%E7%AC%AC2%E7%AB%A0%20.mp3","mediaDownloadUrl":"https://raw.kiko-play-niptan.one/media/download/daily/2022-10-15/RJ418548/2.MP3%E7%89%88/2.%E7%AC%AC2%E7%AB%A0%20.mp3","streamLowQualityUrl":"","duration":1594.749469},{"type":"audio","hash":"418548/12","title":"3.第3章.mp3","workTitle":"【逆レイプ】【オホ声】【連続射精】マッドナースの搾精実験〜敵組織の悪のナースに捕まった貴方は一日中連続搾精で快楽実験のモルモットにされる〜","mediaStreamUrl":"https://raw.kiko-play-niptan.one/media/stream/daily/2022-10-15/RJ418548/2.MP3%E7%89%88/3.%E7%AC%AC3%E7%AB%A0.mp3","mediaDownloadUrl":"https://raw.kiko-play-niptan.one/media/download/daily/2022-10-15/RJ418548/2.MP3%E7%89%88/3.%E7%AC%AC3%E7%AB%A0.mp3","streamLowQualityUrl":"","duration":1093.825344},{"type":"audio","hash":"418548/16","title":"4.第4章 .mp3","workTitle":"【逆レイプ】【オホ声】【連続射精】マッドナースの搾精実験〜敵組織の悪のナースに捕まった貴方は一日中連続搾精で快楽実験のモルモットにされる〜","mediaStreamUrl":"https://raw.kiko-play-niptan.one/media/stream/daily/2022-10-15/RJ418548/2.MP3%E7%89%88/4.%E7%AC%AC4%E7%AB%A0%20.mp3","mediaDownloadUrl":"https://raw.kiko-play-niptan.one/media/download/daily/2022-10-15/RJ418548/2.MP3%E7%89%88/4.%E7%AC%AC4%E7%AB%A0%20.mp3","streamLowQualityUrl":"","duration":1315.265375},{"type":"audio","hash":"418548/20","title":"5.第5章 .mp3","workTitle":"【逆レイプ】【オホ声】【連続射精】マッドナースの搾精実験〜敵組織の悪のナースに捕まった貴方は一日中連続搾精で快楽実験のモルモットにされる〜","mediaStreamUrl":"https://raw.kiko-play-niptan.one/media/stream/daily/2022-10-15/RJ418548/2.MP3%E7%89%88/5.%E7%AC%AC5%E7%AB%A0%20.mp3","mediaDownloadUrl":"https://raw.kiko-play-niptan.one/media/download/daily/2022-10-15/RJ418548/2.MP3%E7%89%88/5.%E7%AC%AC5%E7%AB%A0%20.mp3","streamLowQualityUrl":"","duration":851.5135},{"type":"audio","hash":"418548/25","title":"6.第6章 .mp3","workTitle":"【逆レイプ】【オホ声】【連続射精】マッドナースの搾精実験〜敵組織の悪のナースに捕まった貴方は一日中連続搾精で快楽実験のモルモットにされる〜","mediaStreamUrl":"https://raw.kiko-play-niptan.one/media/stream/daily/2022-10-15/RJ418548/2.MP3%E7%89%88/6.%E7%AC%AC6%E7%AB%A0%20.mp3","mediaDownloadUrl":"https://raw.kiko-play-niptan.one/media/download/daily/2022-10-15/RJ418548/2.MP3%E7%89%88/6.%E7%AC%AC6%E7%AB%A0%20.mp3","streamLowQualityUrl":"","duration":873.743719},{"type":"audio","hash":"418548/29","title":"7.第7章.mp3","workTitle":"【逆レイプ】【オホ声】【連続射精】マッドナースの搾精実験〜敵組織の悪のナースに捕まった貴方は一日中連続搾精で快楽実験のモルモットにされる〜","mediaStreamUrl":"https://raw.kiko-play-niptan.one/media/stream/daily/2022-10-15/RJ418548/2.MP3%E7%89%88/7.%E7%AC%AC7%E7%AB%A0.mp3","mediaDownloadUrl":"https://raw.kiko-play-niptan.one/media/download/daily/2022-10-15/RJ418548/2.MP3%E7%89%88/7.%E7%AC%AC7%E7%AB%A0.mp3","streamLowQualityUrl":"","duration":943.490656},{"type":"audio","hash":"418548/33","title":"8.第8章 .mp3","workTitle":"【逆レイプ】【オホ声】【連続射精】マッドナースの搾精実験〜敵組織の悪のナースに捕まった貴方は一日中連続搾精で快楽実験のモルモットにされる〜","mediaStreamUrl":"https://raw.kiko-play-niptan.one/media/stream/daily/2022-10-15/RJ418548/2.MP3%E7%89%88/8.%E7%AC%AC8%E7%AB%A0%20.mp3","mediaDownloadUrl":"https://raw.kiko-play-niptan.one/media/download/daily/2022-10-15/RJ418548/2.MP3%E7%89%88/8.%E7%AC%AC8%E7%AB%A0%20.mp3","streamLowQualityUrl":"","duration":356.597562},{"type":"audio","hash":"418548/37","title":"9.第8章（白） .mp3","workTitle":"【逆レイプ】【オホ声】【連続射精】マッドナースの搾精実験〜敵組織の悪のナースに捕まった貴方は一日中連続搾精で快楽実験のモルモットにされる〜","mediaStreamUrl":"https://raw.kiko-play-niptan.one/media/stream/daily/2022-10-15/RJ418548/2.MP3%E7%89%88/9.%E7%AC%AC8%E7%AB%A0%EF%BC%88%E7%99%BD%EF%BC%89%20.mp3","mediaDownloadUrl":"https://raw.kiko-play-niptan.one/media/download/daily/2022-10-15/RJ418548/2.MP3%E7%89%88/9.%E7%AC%AC8%E7%AB%A0%EF%BC%88%E7%99%BD%EF%BC%89%20.mp3","streamLowQualityUrl":"","duration":675.657187},{"type":"audio","hash":"418548/41","title":"10.第8章（黒） .mp3","workTitle":"【逆レイプ】【オホ声】【連続射精】マッドナースの搾精実験〜敵組織の悪のナースに捕まった貴方は一日中連続搾精で快楽実験のモルモットにされる〜","mediaStreamUrl":"https://raw.kiko-play-niptan.one/media/stream/daily/2022-10-15/RJ418548/2.MP3%E7%89%88/10.%E7%AC%AC8%E7%AB%A0%EF%BC%88%E9%BB%92%EF%BC%89%20.mp3","mediaDownloadUrl":"https://raw.kiko-play-niptan.one/media/download/daily/2022-10-15/RJ418548/2.MP3%E7%89%88/10.%E7%AC%AC8%E7%AB%A0%EF%BC%88%E9%BB%92%EF%BC%89%20.mp3","streamLowQualityUrl":"","duration":824.973094},{"type":"audio","hash":"418548/45","title":"11.第9章 .mp3","workTitle":"【逆レイプ】【オホ声】【連続射精】マッドナースの搾精実験〜敵組織の悪のナースに捕まった貴方は一日中連続搾精で快楽実験のモルモットにされる〜","mediaStreamUrl":"https://raw.kiko-play-niptan.one/media/stream/daily/2022-10-15/RJ418548/2.MP3%E7%89%88/11.%E7%AC%AC9%E7%AB%A0%20.mp3","mediaDownloadUrl":"https://raw.kiko-play-niptan.one/media/download/daily/2022-10-15/RJ418548/2.MP3%E7%89%88/11.%E7%AC%AC9%E7%AB%A0%20.mp3","streamLowQualityUrl":"","duration":898.063719},{"type":"audio","hash":"418548/49","title":"12.第10章 .mp3","workTitle":"【逆レイプ】【オホ声】【連続射精】マッドナースの搾精実験〜敵組織の悪のナースに捕まった貴方は一日中連続搾精で快楽実験のモルモットにされる〜","mediaStreamUrl":"https://raw.kiko-play-niptan.one/media/stream/daily/2022-10-15/RJ418548/2.MP3%E7%89%88/12.%E7%AC%AC10%E7%AB%A0%20.mp3","mediaDownloadUrl":"https://raw.kiko-play-niptan.one/media/download/daily/2022-10-15/RJ418548/2.MP3%E7%89%88/12.%E7%AC%AC10%E7%AB%A0%20.mp3","streamLowQualityUrl":"","duration":1042.024531}]},{"type":"folder","title":"4.効果音無しMP3","children":[{"type":"audio","hash":"418548/1","title":"0.プロローグ .mp3","workTitle":"【逆レイプ】【オホ声】【連続射精】マッドナースの搾精実験〜敵組織の悪のナースに捕まった貴方は一日中連続搾精で快楽実験のモルモットにされる〜","mediaStreamUrl":"https://raw.kiko-play-niptan.one/media/stream/daily/2022-10-15/RJ418548/4.%E5%8A%B9%E6%9E%9C%E9%9F%B3%E7%84%A1%E3%81%97MP3/0.%E3%83%97%E3%83%AD%E3%83%AD%E3%83%BC%E3%82%B0%20.mp3","mediaDownloadUrl":"https://raw.kiko-play-niptan.one/media/download/daily/2022-10-15/RJ418548/4.%E5%8A%B9%E6%9E%9C%E9%9F%B3%E7%84%A1%E3%81%97MP3/0.%E3%83%97%E3%83%AD%E3%83%AD%E3%83%BC%E3%82%B0%20.mp3","streamLowQualityUrl":"","duration":343.379625},{"type":"audio","hash":"418548/5","title":"1.第1章 .mp3","workTitle":"【逆レイプ】【オホ声】【連続射精】マッドナースの搾精実験〜敵組織の悪のナースに捕まった貴方は一日中連続搾精で快楽実験のモルモットにされる〜","mediaStreamUrl":"https://raw.kiko-play-niptan.one/media/stream/daily/2022-10-15/RJ418548/4.%E5%8A%B9%E6%9E%9C%E9%9F%B3%E7%84%A1%E3%81%97MP3/1.%E7%AC%AC1%E7%AB%A0%20.mp3","mediaDownloadUrl":"https://raw.kiko-play-niptan.one/media/download/daily/2022-10-15/RJ418548/4.%E5%8A%B9%E6%9E%9C%E9%9F%B3%E7%84%A1%E3%81%97MP3/1.%E7%AC%AC1%E7%AB%A0%20.mp3","streamLowQualityUrl":"","duration":1154.795156},{"type":"audio","hash":"418548/9","title":"2.第2章 .mp3","workTitle":"【逆レイプ】【オホ声】【連続射精】マッドナースの搾精実験〜敵組織の悪のナースに捕まった貴方は一日中連続搾精で快楽実験のモルモットにされる〜","mediaStreamUrl":"https://raw.kiko-play-niptan.one/media/stream/daily/2022-10-15/RJ418548/4.%E5%8A%B9%E6%9E%9C%E9%9F%B3%E7%84%A1%E3%81%97MP3/2.%E7%AC%AC2%E7%AB%A0%20.mp3","mediaDownloadUrl":"https://raw.kiko-play-niptan.one/media/download/daily/2022-10-15/RJ418548/4.%E5%8A%B9%E6%9E%9C%E9%9F%B3%E7%84%A1%E3%81%97MP3/2.%E7%AC%AC2%E7%AB%A0%20.mp3","streamLowQualityUrl":"","duration":1589.681687},{"type":"audio","hash":"418548/13","title":"3.第3章.mp3","workTitle":"【逆レイプ】【オホ声】【連続射精】マッドナースの搾精実験〜敵組織の悪のナースに捕まった貴方は一日中連続搾精で快楽実験のモルモットにされる〜","mediaStreamUrl":"https://raw.kiko-play-niptan.one/media/stream/daily/2022-10-15/RJ418548/4.%E5%8A%B9%E6%9E%9C%E9%9F%B3%E7%84%A1%E3%81%97MP3/3.%E7%AC%AC3%E7%AB%A0.mp3","mediaDownloadUrl":"https://raw.kiko-play-niptan.one/media/download/daily/2022-10-15/RJ418548/4.%E5%8A%B9%E6%9E%9C%E9%9F%B3%E7%84%A1%E3%81%97MP3/3.%E7%AC%AC3%E7%AB%A0.mp3","streamLowQualityUrl":"","duration":1089.358406},{"type":"audio","hash":"418548/17","title":"4.第4章 .mp3","workTitle":"【逆レイプ】【オホ声】【連続射精】マッドナースの搾精実験〜敵組織の悪のナースに捕まった貴方は一日中連続搾精で快楽実験のモルモットにされる〜","mediaStreamUrl":"https://raw.kiko-play-niptan.one/media/stream/daily/2022-10-15/RJ418548/4.%E5%8A%B9%E6%9E%9C%E9%9F%B3%E7%84%A1%E3%81%97MP3/4.%E7%AC%AC4%E7%AB%A0%20.mp3","mediaDownloadUrl":"https://raw.kiko-play-niptan.one/media/download/daily/2022-10-15/RJ418548/4.%E5%8A%B9%E6%9E%9C%E9%9F%B3%E7%84%A1%E3%81%97MP3/4.%E7%AC%AC4%E7%AB%A0%20.mp3","streamLowQualityUrl":"","duration":1310.772312},{"type":"audio","hash":"418548/21","title":"5.第5章 .mp3","workTitle":"【逆レイプ】【オホ声】【連続射精】マッドナースの搾精実験〜敵組織の悪のナースに捕まった貴方は一日中連続搾精で快楽実験のモルモットにされる〜","mediaStreamUrl":"https://raw.kiko-play-niptan.one/media/stream/daily/2022-10-15/RJ418548/4.%E5%8A%B9%E6%9E%9C%E9%9F%B3%E7%84%A1%E3%81%97MP3/5.%E7%AC%AC5%E7%AB%A0%20.mp3","mediaDownloadUrl":"https://raw.kiko-play-niptan.one/media/download/daily/2022-10-15/RJ418548/4.%E5%8A%B9%E6%9E%9C%E9%9F%B3%E7%84%A1%E3%81%97MP3/5.%E7%AC%AC5%E7%AB%A0%20.mp3","streamLowQualityUrl":"","duration":843.781281},{"type":"audio","hash":"418548/26","title":"6.第6章 .mp3","workTitle":"【逆レイプ】【オホ声】【連続射精】マッドナースの搾精実験〜敵組織の悪のナースに捕まった貴方は一日中連続搾精で快楽実験のモルモットにされる〜","mediaStreamUrl":"https://raw.kiko-play-niptan.one/media/stream/daily/2022-10-15/RJ418548/4.%E5%8A%B9%E6%9E%9C%E9%9F%B3%E7%84%A1%E3%81%97MP3/6.%E7%AC%AC6%E7%AB%A0%20.mp3","mediaDownloadUrl":"https://raw.kiko-play-niptan.one/media/download/daily/2022-10-15/RJ418548/4.%E5%8A%B9%E6%9E%9C%E9%9F%B3%E7%84%A1%E3%81%97MP3/6.%E7%AC%AC6%E7%AB%A0%20.mp3","streamLowQualityUrl":"","duration":873.743719},{"type":"audio","hash":"418548/30","title":"7.第7章.mp3","workTitle":"【逆レイプ】【オホ声】【連続射精】マッドナースの搾精実験〜敵組織の悪のナースに捕まった貴方は一日中連続搾精で快楽実験のモルモットにされる〜","mediaStreamUrl":"https://raw.kiko-play-niptan.one/media/stream/daily/2022-10-15/RJ418548/4.%E5%8A%B9%E6%9E%9C%E9%9F%B3%E7%84%A1%E3%81%97MP3/7.%E7%AC%AC7%E7%AB%A0.mp3","mediaDownloadUrl":"https://raw.kiko-play-niptan.one/media/download/daily/2022-10-15/RJ418548/4.%E5%8A%B9%E6%9E%9C%E9%9F%B3%E7%84%A1%E3%81%97MP3/7.%E7%AC%AC7%E7%AB%A0.mp3","streamLowQualityUrl":"","duration":938.004937},{"type":"audio","hash":"418548/34","title":"8.第8章 .mp3","workTitle":"【逆レイプ】【オホ声】【連続射精】マッドナースの搾精実験〜敵組織の悪のナースに捕まった貴方は一日中連続搾精で快楽実験のモルモットにされる〜","mediaStreamUrl":"https://raw.kiko-play-niptan.one/media/stream/daily/2022-10-15/RJ418548/4.%E5%8A%B9%E6%9E%9C%E9%9F%B3%E7%84%A1%E3%81%97MP3/8.%E7%AC%AC8%E7%AB%A0%20.mp3","mediaDownloadUrl":"https://raw.kiko-play-niptan.one/media/download/daily/2022-10-15/RJ418548/4.%E5%8A%B9%E6%9E%9C%E9%9F%B3%E7%84%A1%E3%81%97MP3/8.%E7%AC%AC8%E7%AB%A0%20.mp3","streamLowQualityUrl":"","duration":353.64575},{"type":"audio","hash":"418548/38","title":"9.第8章（白） .mp3","workTitle":"【逆レイプ】【オホ声】【連続射精】マッドナースの搾精実験〜敵組織の悪のナースに捕まった貴方は一日中連続搾精で快楽実験のモルモットにされる〜","mediaStreamUrl":"https://raw.kiko-play-niptan.one/media/stream/daily/2022-10-15/RJ418548/4.%E5%8A%B9%E6%9E%9C%E9%9F%B3%E7%84%A1%E3%81%97MP3/9.%E7%AC%AC8%E7%AB%A0%EF%BC%88%E7%99%BD%EF%BC%89%20.mp3","mediaDownloadUrl":"https://raw.kiko-play-niptan.one/media/download/daily/2022-10-15/RJ418548/4.%E5%8A%B9%E6%9E%9C%E9%9F%B3%E7%84%A1%E3%81%97MP3/9.%E7%AC%AC8%E7%AB%A0%EF%BC%88%E7%99%BD%EF%BC%89%20.mp3","streamLowQualityUrl":"","duration":675.657187},{"type":"audio","hash":"418548/42","title":"10.第8章（黒） .mp3","workTitle":"【逆レイプ】【オホ声】【連続射精】マッドナースの搾精実験〜敵組織の悪のナースに捕まった貴方は一日中連続搾精で快楽実験のモルモットにされる〜","mediaStreamUrl":"https://raw.kiko-play-niptan.one/media/stream/daily/2022-10-15/RJ418548/4.%E5%8A%B9%E6%9E%9C%E9%9F%B3%E7%84%A1%E3%81%97MP3/10.%E7%AC%AC8%E7%AB%A0%EF%BC%88%E9%BB%92%EF%BC%89%20.mp3","mediaDownloadUrl":"https://raw.kiko-play-niptan.one/media/download/daily/2022-10-15/RJ418548/4.%E5%8A%B9%E6%9E%9C%E9%9F%B3%E7%84%A1%E3%81%97MP3/10.%E7%AC%AC8%E7%AB%A0%EF%BC%88%E9%BB%92%EF%BC%89%20.mp3","streamLowQualityUrl":"","duration":824.973094},{"type":"audio","hash":"418548/46","title":"11.第9章 .mp3","workTitle":"【逆レイプ】【オホ声】【連続射精】マッドナースの搾精実験〜敵組織の悪のナースに捕まった貴方は一日中連続搾精で快楽実験のモルモットにされる〜","mediaStreamUrl":"https://raw.kiko-play-niptan.one/media/stream/daily/2022-10-15/RJ418548/4.%E5%8A%B9%E6%9E%9C%E9%9F%B3%E7%84%A1%E3%81%97MP3/11.%E7%AC%AC9%E7%AB%A0%20.mp3","mediaDownloadUrl":"https://raw.kiko-play-niptan.one/media/download/daily/2022-10-15/RJ418548/4.%E5%8A%B9%E6%9E%9C%E9%9F%B3%E7%84%A1%E3%81%97MP3/11.%E7%AC%AC9%E7%AB%A0%20.mp3","streamLowQualityUrl":"","duration":898.063719},{"type":"audio","hash":"418548/50","title":"12.第10章 .mp3","workTitle":"【逆レイプ】【オホ声】【連続射精】マッドナースの搾精実験〜敵組織の悪のナースに捕まった貴方は一日中連続搾精で快楽実験のモルモットにされる〜","mediaStreamUrl":"https://raw.kiko-play-niptan.one/media/stream/daily/2022-10-15/RJ418548/4.%E5%8A%B9%E6%9E%9C%E9%9F%B3%E7%84%A1%E3%81%97MP3/12.%E7%AC%AC10%E7%AB%A0%20.mp3","mediaDownloadUrl":"https://raw.kiko-play-niptan.one/media/download/daily/2022-10-15/RJ418548/4.%E5%8A%B9%E6%9E%9C%E9%9F%B3%E7%84%A1%E3%81%97MP3/12.%E7%AC%AC10%E7%AB%A0%20.mp3","streamLowQualityUrl":"","duration":1041.528219}]},{"type":"folder","title":"3.効果音無しWAV版","children":[{"type":"audio","hash":"418548/2","title":"0.プロローグ .wav","workTitle":"【逆レイプ】【オホ声】【連続射精】マッドナースの搾精実験〜敵組織の悪のナースに捕まった貴方は一日中連続搾精で快楽実験のモルモットにされる〜","mediaStreamUrl":"https://raw.kiko-play-niptan.one/media/stream/daily/2022-10-15/RJ418548/3.%E5%8A%B9%E6%9E%9C%E9%9F%B3%E7%84%A1%E3%81%97WAV%E7%89%88/0.%E3%83%97%E3%83%AD%E3%83%AD%E3%83%BC%E3%82%B0%20.wav","mediaDownloadUrl":"https://raw.kiko-play-niptan.one/media/download/daily/2022-10-15/RJ418548/3.%E5%8A%B9%E6%9E%9C%E9%9F%B3%E7%84%A1%E3%81%97WAV%E7%89%88/0.%E3%83%97%E3%83%AD%E3%83%AD%E3%83%BC%E3%82%B0%20.wav","streamLowQualityUrl":"https://fast.kiko-play-niptan.one/media/stream/daily/2022-10-15/RJ418548/3.%E5%8A%B9%E6%9E%9C%E9%9F%B3%E7%84%A1%E3%81%97WAV%E7%89%88/0.%E3%83%97%E3%83%AD%E3%83%AD%E3%83%BC%E3%82%B0%20.m4a","duration":343.303107},{"type":"audio","hash":"418548/6","title":"1.第1章 .wav","workTitle":"【逆レイプ】【オホ声】【連続射精】マッドナースの搾精実験〜敵組織の悪のナースに捕まった貴方は一日中連続搾精で快楽実験のモルモットにされる〜","mediaStreamUrl":"https://raw.kiko-play-niptan.one/media/stream/daily/2022-10-15/RJ418548/3.%E5%8A%B9%E6%9E%9C%E9%9F%B3%E7%84%A1%E3%81%97WAV%E7%89%88/1.%E7%AC%AC1%E7%AB%A0%20.wav","mediaDownloadUrl":"https://raw.kiko-play-niptan.one/media/download/daily/2022-10-15/RJ418548/3.%E5%8A%B9%E6%9E%9C%E9%9F%B3%E7%84%A1%E3%81%97WAV%E7%89%88/1.%E7%AC%AC1%E7%AB%A0%20.wav","streamLowQualityUrl":"https://fast.kiko-play-niptan.one/media/stream/daily/2022-10-15/RJ418548/3.%E5%8A%B9%E6%9E%9C%E9%9F%B3%E7%84%A1%E3%81%97WAV%E7%89%88/1.%E7%AC%AC1%E7%AB%A0%20.m4a","duration":1154.729161},{"type":"audio","hash":"418548/10","title":"2.第2章 .wav","workTitle":"【逆レイプ】【オホ声】【連続射精】マッドナースの搾精実験〜敵組織の悪のナースに捕まった貴方は一日中連続搾精で快楽実験のモルモットにされる〜","mediaStreamUrl":"https://raw.kiko-play-niptan.one/media/stream/daily/2022-10-15/RJ418548/3.%E5%8A%B9%E6%9E%9C%E9%9F%B3%E7%84%A1%E3%81%97WAV%E7%89%88/2.%E7%AC%AC2%E7%AB%A0%20.wav","mediaDownloadUrl":"https://raw.kiko-play-niptan.one/media/download/daily/2022-10-15/RJ418548/3.%E5%8A%B9%E6%9E%9C%E9%9F%B3%E7%84%A1%E3%81%97WAV%E7%89%88/2.%E7%AC%AC2%E7%AB%A0%20.wav","streamLowQualityUrl":"https://fast.kiko-play-niptan.one/media/stream/daily/2022-10-15/RJ418548/3.%E5%8A%B9%E6%9E%9C%E9%9F%B3%E7%84%A1%E3%81%97WAV%E7%89%88/2.%E7%AC%AC2%E7%AB%A0%20.m4a","duration":1589.627098},{"type":"audio","hash":"418548/14","title":"3.第3章.wav","workTitle":"【逆レイプ】【オホ声】【連続射精】マッドナースの搾精実験〜敵組織の悪のナースに捕まった貴方は一日中連続搾精で快楽実験のモルモットにされる〜","mediaStreamUrl":"https://raw.kiko-play-niptan.one/media/stream/daily/2022-10-15/RJ418548/3.%E5%8A%B9%E6%9E%9C%E9%9F%B3%E7%84%A1%E3%81%97WAV%E7%89%88/3.%E7%AC%AC3%E7%AB%A0.wav","mediaDownloadUrl":"https://raw.kiko-play-niptan.one/media/download/daily/2022-10-15/RJ418548/3.%E5%8A%B9%E6%9E%9C%E9%9F%B3%E7%84%A1%E3%81%97WAV%E7%89%88/3.%E7%AC%AC3%E7%AB%A0.wav","streamLowQualityUrl":"https://fast.kiko-play-niptan.one/media/stream/daily/2022-10-15/RJ418548/3.%E5%8A%B9%E6%9E%9C%E9%9F%B3%E7%84%A1%E3%81%97WAV%E7%89%88/3.%E7%AC%AC3%E7%AB%A0.m4a","duration":1089.291519},{"type":"audio","hash":"418548/18","title":"4.第4章 .wav","workTitle":"【逆レイプ】【オホ声】【連続射精】マッドナースの搾精実験〜敵組織の悪のナースに捕まった貴方は一日中連続搾精で快楽実験のモルモットにされる〜","mediaStreamUrl":"https://raw.kiko-play-niptan.one/media/stream/daily/2022-10-15/RJ418548/3.%E5%8A%B9%E6%9E%9C%E9%9F%B3%E7%84%A1%E3%81%97WAV%E7%89%88/4.%E7%AC%AC4%E7%AB%A0%20.wav","mediaDownloadUrl":"https://raw.kiko-play-niptan.one/media/download/daily/2022-10-15/RJ418548/3.%E5%8A%B9%E6%9E%9C%E9%9F%B3%E7%84%A1%E3%81%97WAV%E7%89%88/4.%E7%AC%AC4%E7%AB%A0%20.wav","streamLowQualityUrl":"https://fast.kiko-play-niptan.one/media/stream/daily/2022-10-15/RJ418548/3.%E5%8A%B9%E6%9E%9C%E9%9F%B3%E7%84%A1%E3%81%97WAV%E7%89%88/4.%E7%AC%AC4%E7%AB%A0%20.m4a","duration":1310.708322},{"type":"audio","hash":"418548/22","title":"5.第5章 .wav","workTitle":"【逆レイプ】【オホ声】【連続射精】マッドナースの搾精実験〜敵組織の悪のナースに捕まった貴方は一日中連続搾精で快楽実験のモルモットにされる〜","mediaStreamUrl":"https://raw.kiko-play-niptan.one/media/stream/daily/2022-10-15/RJ418548/3.%E5%8A%B9%E6%9E%9C%E9%9F%B3%E7%84%A1%E3%81%97WAV%E7%89%88/5.%E7%AC%AC5%E7%AB%A0%20.wav","mediaDownloadUrl":"https://raw.kiko-play-niptan.one/media/download/daily/2022-10-15/RJ418548/3.%E5%8A%B9%E6%9E%9C%E9%9F%B3%E7%84%A1%E3%81%97WAV%E7%89%88/5.%E7%AC%AC5%E7%AB%A0%20.wav","streamLowQualityUrl":"https://fast.kiko-play-niptan.one/media/stream/daily/2022-10-15/RJ418548/3.%E5%8A%B9%E6%9E%9C%E9%9F%B3%E7%84%A1%E3%81%97WAV%E7%89%88/5.%E7%AC%AC5%E7%AB%A0%20.m4a","duration":843.708345},{"type":"audio","hash":"418548/27","title":"6.第6章 .wav","workTitle":"【逆レイプ】【オホ声】【連続射精】マッドナースの搾精実験〜敵組織の悪のナースに捕まった貴方は一日中連続搾精で快楽実験のモルモットにされる〜","mediaStreamUrl":"https://raw.kiko-play-niptan.one/media/stream/daily/2022-10-15/RJ418548/3.%E5%8A%B9%E6%9E%9C%E9%9F%B3%E7%84%A1%E3%81%97WAV%E7%89%88/6.%E7%AC%AC6%E7%AB%A0%20.wav","mediaDownloadUrl":"https://raw.kiko-play-niptan.one/media/download/daily/2022-10-15/RJ418548/3.%E5%8A%B9%E6%9E%9C%E9%9F%B3%E7%84%A1%E3%81%97WAV%E7%89%88/6.%E7%AC%AC6%E7%AB%A0%20.wav","streamLowQualityUrl":"https://fast.kiko-play-niptan.one/media/stream/daily/2022-10-15/RJ418548/3.%E5%8A%B9%E6%9E%9C%E9%9F%B3%E7%84%A1%E3%81%97WAV%E7%89%88/6.%E7%AC%AC6%E7%AB%A0%20.m4a","duration":873.687483},{"type":"audio","hash":"418548/31","title":"7.第7章.wav","workTitle":"【逆レイプ】【オホ声】【連続射精】マッドナースの搾精実験〜敵組織の悪のナースに捕まった貴方は一日中連続搾精で快楽実験のモルモットにされる〜","mediaStreamUrl":"https://raw.kiko-play-niptan.one/media/stream/daily/2022-10-15/RJ418548/3.%E5%8A%B9%E6%9E%9C%E9%9F%B3%E7%84%A1%E3%81%97WAV%E7%89%88/7.%E7%AC%AC7%E7%AB%A0.wav","mediaDownloadUrl":"https://raw.kiko-play-niptan.one/media/download/daily/2022-10-15/RJ418548/3.%E5%8A%B9%E6%9E%9C%E9%9F%B3%E7%84%A1%E3%81%97WAV%E7%89%88/7.%E7%AC%AC7%E7%AB%A0.wav","streamLowQualityUrl":"https://fast.kiko-play-niptan.one/media/stream/daily/2022-10-15/RJ418548/3.%E5%8A%B9%E6%9E%9C%E9%9F%B3%E7%84%A1%E3%81%97WAV%E7%89%88/7.%E7%AC%AC7%E7%AB%A0.m4a","duration":937.937483},{"type":"audio","hash":"418548/35","title":"8.第8章 .wav","workTitle":"【逆レイプ】【オホ声】【連続射精】マッドナースの搾精実験〜敵組織の悪のナースに捕まった貴方は一日中連続搾精で快楽実験のモルモットにされる〜","mediaStreamUrl":"https://raw.kiko-play-niptan.one/media/stream/daily/2022-10-15/RJ418548/3.%E5%8A%B9%E6%9E%9C%E9%9F%B3%E7%84%A1%E3%81%97WAV%E7%89%88/8.%E7%AC%AC8%E7%AB%A0%20.wav","mediaDownloadUrl":"https://raw.kiko-play-niptan.one/media/download/daily/2022-10-15/RJ418548/3.%E5%8A%B9%E6%9E%9C%E9%9F%B3%E7%84%A1%E3%81%97WAV%E7%89%88/8.%E7%AC%AC8%E7%AB%A0%20.wav","streamLowQualityUrl":"https://fast.kiko-play-niptan.one/media/stream/daily/2022-10-15/RJ418548/3.%E5%8A%B9%E6%9E%9C%E9%9F%B3%E7%84%A1%E3%81%97WAV%E7%89%88/8.%E7%AC%AC8%E7%AB%A0%20.m4a","duration":353.575873},{"type":"audio","hash":"418548/39","title":"9.第8章（白） .wav","workTitle":"【逆レイプ】【オホ声】【連続射精】マッドナースの搾精実験〜敵組織の悪のナースに捕まった貴方は一日中連続搾精で快楽実験のモルモットにされる〜","mediaStreamUrl":"https://raw.kiko-play-niptan.one/media/stream/daily/2022-10-15/RJ418548/3.%E5%8A%B9%E6%9E%9C%E9%9F%B3%E7%84%A1%E3%81%97WAV%E7%89%88/9.%E7%AC%AC8%E7%AB%A0%EF%BC%88%E7%99%BD%EF%BC%89%20.wav","mediaDownloadUrl":"https://raw.kiko-play-niptan.one/media/download/daily/2022-10-15/RJ418548/3.%E5%8A%B9%E6%9E%9C%E9%9F%B3%E7%84%A1%E3%81%97WAV%E7%89%88/9.%E7%AC%AC8%E7%AB%A0%EF%BC%88%E7%99%BD%EF%BC%89%20.wav","streamLowQualityUrl":"https://fast.kiko-play-niptan.one/media/stream/daily/2022-10-15/RJ418548/3.%E5%8A%B9%E6%9E%9C%E9%9F%B3%E7%84%A1%E3%81%97WAV%E7%89%88/9.%E7%AC%AC8%E7%AB%A0%EF%BC%88%E7%99%BD%EF%BC%89%20.m4a","duration":675.583333},{"type":"audio","hash":"418548/43","title":"10.第8章（黒） .wav","workTitle":"【逆レイプ】【オホ声】【連続射精】マッドナースの搾精実験〜敵組織の悪のナースに捕まった貴方は一日中連続搾精で快楽実験のモルモットにされる〜","mediaStreamUrl":"https://raw.kiko-play-niptan.one/media/stream/daily/2022-10-15/RJ418548/3.%E5%8A%B9%E6%9E%9C%E9%9F%B3%E7%84%A1%E3%81%97WAV%E7%89%88/10.%E7%AC%AC8%E7%AB%A0%EF%BC%88%E9%BB%92%EF%BC%89%20.wav","mediaDownloadUrl":"https://raw.kiko-play-niptan.one/media/download/daily/2022-10-15/RJ418548/3.%E5%8A%B9%E6%9E%9C%E9%9F%B3%E7%84%A1%E3%81%97WAV%E7%89%88/10.%E7%AC%AC8%E7%AB%A0%EF%BC%88%E9%BB%92%EF%BC%89%20.wav","streamLowQualityUrl":"https://fast.kiko-play-niptan.one/media/stream/daily/2022-10-15/RJ418548/3.%E5%8A%B9%E6%9E%9C%E9%9F%B3%E7%84%A1%E3%81%97WAV%E7%89%88/10.%E7%AC%AC8%E7%AB%A0%EF%BC%88%E9%BB%92%EF%BC%89%20.m4a","duration":824.903107},{"type":"audio","hash":"418548/47","title":"11.第9章 .wav","workTitle":"【逆レイプ】【オホ声】【連続射精】マッドナースの搾精実験〜敵組織の悪のナースに捕まった貴方は一日中連続搾精で快楽実験のモルモットにされる〜","mediaStreamUrl":"https://raw.kiko-play-niptan.one/media/stream/daily/2022-10-15/RJ418548/3.%E5%8A%B9%E6%9E%9C%E9%9F%B3%E7%84%A1%E3%81%97WAV%E7%89%88/11.%E7%AC%AC9%E7%AB%A0%20.wav","mediaDownloadUrl":"https://raw.kiko-play-niptan.one/media/download/daily/2022-10-15/RJ418548/3.%E5%8A%B9%E6%9E%9C%E9%9F%B3%E7%84%A1%E3%81%97WAV%E7%89%88/11.%E7%AC%AC9%E7%AB%A0%20.wav","streamLowQualityUrl":"https://fast.kiko-play-niptan.one/media/stream/daily/2022-10-15/RJ418548/3.%E5%8A%B9%E6%9E%9C%E9%9F%B3%E7%84%A1%E3%81%97WAV%E7%89%88/11.%E7%AC%AC9%E7%AB%A0%20.m4a","duration":898},{"type":"audio","hash":"418548/51","title":"12.第10章 .wav","workTitle":"【逆レイプ】【オホ声】【連続射精】マッドナースの搾精実験〜敵組織の悪のナースに捕まった貴方は一日中連続搾精で快楽実験のモルモットにされる〜","mediaStreamUrl":"https://raw.kiko-play-niptan.one/media/stream/daily/2022-10-15/RJ418548/3.%E5%8A%B9%E6%9E%9C%E9%9F%B3%E7%84%A1%E3%81%97WAV%E7%89%88/12.%E7%AC%AC10%E7%AB%A0%20.wav","mediaDownloadUrl":"https://raw.kiko-play-niptan.one/media/download/daily/2022-10-15/RJ418548/3.%E5%8A%B9%E6%9E%9C%E9%9F%B3%E7%84%A1%E3%81%97WAV%E7%89%88/12.%E7%AC%AC10%E7%AB%A0%20.wav","streamLowQualityUrl":"https://fast.kiko-play-niptan.one/media/stream/daily/2022-10-15/RJ418548/3.%E5%8A%B9%E6%9E%9C%E9%9F%B3%E7%84%A1%E3%81%97WAV%E7%89%88/12.%E7%AC%AC10%E7%AB%A0%20.m4a","duration":1041.458322}]},{"type":"folder","title":"1.本編WAV版（高音質）","children":[{"type":"audio","hash":"418548/3","title":"0.プロローグ.wav","workTitle":"【逆レイプ】【オホ声】【連続射精】マッドナースの搾精実験〜敵組織の悪のナースに捕まった貴方は一日中連続搾精で快楽実験のモルモットにされる〜","mediaStreamUrl":"https://raw.kiko-play-niptan.one/media/stream/daily/2022-10-15/RJ418548/1.%E6%9C%AC%E7%B7%A8WAV%E7%89%88%EF%BC%88%E9%AB%98%E9%9F%B3%E8%B3%AA%EF%BC%89/0.%E3%83%97%E3%83%AD%E3%83%AD%E3%83%BC%E3%82%B0.wav","mediaDownloadUrl":"https://raw.kiko-play-niptan.one/media/download/daily/2022-10-15/RJ418548/1.%E6%9C%AC%E7%B7%A8WAV%E7%89%88%EF%BC%88%E9%AB%98%E9%9F%B3%E8%B3%AA%EF%BC%89/0.%E3%83%97%E3%83%AD%E3%83%AD%E3%83%BC%E3%82%B0.wav","streamLowQualityUrl":"https://fast.kiko-play-niptan.one/media/stream/daily/2022-10-15/RJ418548/1.%E6%9C%AC%E7%B7%A8WAV%E7%89%88%EF%BC%88%E9%AB%98%E9%9F%B3%E8%B3%AA%EF%BC%89/0.%E3%83%97%E3%83%AD%E3%83%AD%E3%83%BC%E3%82%B0.m4a","duration":343.303107},{"type":"audio","hash":"418548/7","title":"1.第1章 .wav","workTitle":"【逆レイプ】【オホ声】【連続射精】マッドナースの搾精実験〜敵組織の悪のナースに捕まった貴方は一日中連続搾精で快楽実験のモルモットにされる〜","mediaStreamUrl":"https://raw.kiko-play-niptan.one/media/stream/daily/2022-10-15/RJ418548/1.%E6%9C%AC%E7%B7%A8WAV%E7%89%88%EF%BC%88%E9%AB%98%E9%9F%B3%E8%B3%AA%EF%BC%89/1.%E7%AC%AC1%E7%AB%A0%20.wav","mediaDownloadUrl":"https://raw.kiko-play-niptan.one/media/download/daily/2022-10-15/RJ418548/1.%E6%9C%AC%E7%B7%A8WAV%E7%89%88%EF%BC%88%E9%AB%98%E9%9F%B3%E8%B3%AA%EF%BC%89/1.%E7%AC%AC1%E7%AB%A0%20.wav","streamLowQualityUrl":"https://fast.kiko-play-niptan.one/media/stream/daily/2022-10-15/RJ418548/1.%E6%9C%AC%E7%B7%A8WAV%E7%89%88%EF%BC%88%E9%AB%98%E9%9F%B3%E8%B3%AA%EF%BC%89/1.%E7%AC%AC1%E7%AB%A0%20.m4a","duration":1158.729161},{"type":"audio","hash":"418548/11","title":"2.第2章 .wav","workTitle":"【逆レイプ】【オホ声】【連続射精】マッドナースの搾精実験〜敵組織の悪のナースに捕まった貴方は一日中連続搾精で快楽実験のモルモットにされる〜","mediaStreamUrl":"https://raw.kiko-play-niptan.one/media/stream/daily/2022-10-15/RJ418548/1.%E6%9C%AC%E7%B7%A8WAV%E7%89%88%EF%BC%88%E9%AB%98%E9%9F%B3%E8%B3%AA%EF%BC%89/2.%E7%AC%AC2%E7%AB%A0%20.wav","mediaDownloadUrl":"https://raw.kiko-play-niptan.one/media/download/daily/2022-10-15/RJ418548/1.%E6%9C%AC%E7%B7%A8WAV%E7%89%88%EF%BC%88%E9%AB%98%E9%9F%B3%E8%B3%AA%EF%BC%89/2.%E7%AC%AC2%E7%AB%A0%20.wav","streamLowQualityUrl":"https://fast.kiko-play-niptan.one/media/stream/daily/2022-10-15/RJ418548/1.%E6%9C%AC%E7%B7%A8WAV%E7%89%88%EF%BC%88%E9%AB%98%E9%9F%B3%E8%B3%AA%EF%BC%89/2.%E7%AC%AC2%E7%AB%A0%20.m4a","duration":1594.674989},{"type":"audio","hash":"418548/15","title":"3.第3章.wav","workTitle":"【逆レイプ】【オホ声】【連続射精】マッドナースの搾精実験〜敵組織の悪のナースに捕まった貴方は一日中連続搾精で快楽実験のモルモットにされる〜","mediaStreamUrl":"https://raw.kiko-play-niptan.one/media/stream/daily/2022-10-15/RJ418548/1.%E6%9C%AC%E7%B7%A8WAV%E7%89%88%EF%BC%88%E9%AB%98%E9%9F%B3%E8%B3%AA%EF%BC%89/3.%E7%AC%AC3%E7%AB%A0.wav","mediaDownloadUrl":"https://raw.kiko-play-niptan.one/media/download/daily/2022-10-15/RJ418548/1.%E6%9C%AC%E7%B7%A8WAV%E7%89%88%EF%BC%88%E9%AB%98%E9%9F%B3%E8%B3%AA%EF%BC%89/3.%E7%AC%AC3%E7%AB%A0.wav","streamLowQualityUrl":"https://fast.kiko-play-niptan.one/media/stream/daily/2022-10-15/RJ418548/1.%E6%9C%AC%E7%B7%A8WAV%E7%89%88%EF%BC%88%E9%AB%98%E9%9F%B3%E8%B3%AA%EF%BC%89/3.%E7%AC%AC3%E7%AB%A0.m4a","duration":1093.749751},{"type":"audio","hash":"418548/19","title":"4.第4章 .wav","workTitle":"【逆レイプ】【オホ声】【連続射精】マッドナースの搾精実験〜敵組織の悪のナースに捕まった貴方は一日中連続搾精で快楽実験のモルモットにされる〜","mediaStreamUrl":"https://raw.kiko-play-niptan.one/media/stream/daily/2022-10-15/RJ418548/1.%E6%9C%AC%E7%B7%A8WAV%E7%89%88%EF%BC%88%E9%AB%98%E9%9F%B3%E8%B3%AA%EF%BC%89/4.%E7%AC%AC4%E7%AB%A0%20.wav","mediaDownloadUrl":"https://raw.kiko-play-niptan.one/media/download/daily/2022-10-15/RJ418548/1.%E6%9C%AC%E7%B7%A8WAV%E7%89%88%EF%BC%88%E9%AB%98%E9%9F%B3%E8%B3%AA%EF%BC%89/4.%E7%AC%AC4%E7%AB%A0%20.wav","streamLowQualityUrl":"https://fast.kiko-play-niptan.one/media/stream/daily/2022-10-15/RJ418548/1.%E6%9C%AC%E7%B7%A8WAV%E7%89%88%EF%BC%88%E9%AB%98%E9%9F%B3%E8%B3%AA%EF%BC%89/4.%E7%AC%AC4%E7%AB%A0%20.m4a","duration":1315.208322},{"type":"audio","hash":"418548/23","title":"5.第5章 .wav","workTitle":"【逆レイプ】【オホ声】【連続射精】マッドナースの搾精実験〜敵組織の悪のナースに捕まった貴方は一日中連続搾精で快楽実験のモルモットにされる〜","mediaStreamUrl":"https://raw.kiko-play-niptan.one/media/stream/daily/2022-10-15/RJ418548/1.%E6%9C%AC%E7%B7%A8WAV%E7%89%88%EF%BC%88%E9%AB%98%E9%9F%B3%E8%B3%AA%EF%BC%89/5.%E7%AC%AC5%E7%AB%A0%20.wav","mediaDownloadUrl":"https://raw.kiko-play-niptan.one/media/download/daily/2022-10-15/RJ418548/1.%E6%9C%AC%E7%B7%A8WAV%E7%89%88%EF%BC%88%E9%AB%98%E9%9F%B3%E8%B3%AA%EF%BC%89/5.%E7%AC%AC5%E7%AB%A0%20.wav","streamLowQualityUrl":"https://fast.kiko-play-niptan.one/media/stream/daily/2022-10-15/RJ418548/1.%E6%9C%AC%E7%B7%A8WAV%E7%89%88%EF%BC%88%E9%AB%98%E9%9F%B3%E8%B3%AA%EF%BC%89/5.%E7%AC%AC5%E7%AB%A0%20.m4a","duration":851.458345},{"type":"audio","hash":"418548/28","title":"6.第6章 .wav","workTitle":"【逆レイプ】【オホ声】【連続射精】マッドナースの搾精実験〜敵組織の悪のナースに捕まった貴方は一日中連続搾精で快楽実験のモルモットにされる〜","mediaStreamUrl":"https://raw.kiko-play-niptan.one/media/stream/daily/2022-10-15/RJ418548/1.%E6%9C%AC%E7%B7%A8WAV%E7%89%88%EF%BC%88%E9%AB%98%E9%9F%B3%E8%B3%AA%EF%BC%89/6.%E7%AC%AC6%E7%AB%A0%20.wav","mediaDownloadUrl":"https://raw.kiko-play-niptan.one/media/download/daily/2022-10-15/RJ418548/1.%E6%9C%AC%E7%B7%A8WAV%E7%89%88%EF%BC%88%E9%AB%98%E9%9F%B3%E8%B3%AA%EF%BC%89/6.%E7%AC%AC6%E7%AB%A0%20.wav","streamLowQualityUrl":"https://fast.kiko-play-niptan.one/media/stream/daily/2022-10-15/RJ418548/1.%E6%9C%AC%E7%B7%A8WAV%E7%89%88%EF%BC%88%E9%AB%98%E9%9F%B3%E8%B3%AA%EF%BC%89/6.%E7%AC%AC6%E7%AB%A0%20.m4a","duration":873.687483},{"type":"audio","hash":"418548/32","title":"7.第7章.wav","workTitle":"【逆レイプ】【オホ声】【連続射精】マッドナースの搾精実験〜敵組織の悪のナースに捕まった貴方は一日中連続搾精で快楽実験のモルモットにされる〜","mediaStreamUrl":"https://raw.kiko-play-niptan.one/media/stream/daily/2022-10-15/RJ418548/1.%E6%9C%AC%E7%B7%A8WAV%E7%89%88%EF%BC%88%E9%AB%98%E9%9F%B3%E8%B3%AA%EF%BC%89/7.%E7%AC%AC7%E7%AB%A0.wav","mediaDownloadUrl":"https://raw.kiko-play-niptan.one/media/download/daily/2022-10-15/RJ418548/1.%E6%9C%AC%E7%B7%A8WAV%E7%89%88%EF%BC%88%E9%AB%98%E9%9F%B3%E8%B3%AA%EF%BC%89/7.%E7%AC%AC7%E7%AB%A0.wav","streamLowQualityUrl":"https://fast.kiko-play-niptan.one/media/stream/daily/2022-10-15/RJ418548/1.%E6%9C%AC%E7%B7%A8WAV%E7%89%88%EF%BC%88%E9%AB%98%E9%9F%B3%E8%B3%AA%EF%BC%89/7.%E7%AC%AC7%E7%AB%A0.m4a","duration":943.437483},{"type":"audio","hash":"418548/36","title":"8.第8章 .wav","workTitle":"【逆レイプ】【オホ声】【連続射精】マッドナースの搾精実験〜敵組織の悪のナースに捕まった貴方は一日中連続搾精で快楽実験のモルモットにされる〜","mediaStreamUrl":"https://raw.kiko-play-niptan.one/media/stream/daily/2022-10-15/RJ418548/1.%E6%9C%AC%E7%B7%A8WAV%E7%89%88%EF%BC%88%E9%AB%98%E9%9F%B3%E8%B3%AA%EF%BC%89/8.%E7%AC%AC8%E7%AB%A0%20.wav","mediaDownloadUrl":"https://raw.kiko-play-niptan.one/media/download/daily/2022-10-15/RJ418548/1.%E6%9C%AC%E7%B7%A8WAV%E7%89%88%EF%BC%88%E9%AB%98%E9%9F%B3%E8%B3%AA%EF%BC%89/8.%E7%AC%AC8%E7%AB%A0%20.wav","streamLowQualityUrl":"https://fast.kiko-play-niptan.one/media/stream/daily/2022-10-15/RJ418548/1.%E6%9C%AC%E7%B7%A8WAV%E7%89%88%EF%BC%88%E9%AB%98%E9%9F%B3%E8%B3%AA%EF%BC%89/8.%E7%AC%AC8%E7%AB%A0%20.m4a","duration":356.531247},{"type":"audio","hash":"418548/40","title":"9.第8章（白） .wav","workTitle":"【逆レイプ】【オホ声】【連続射精】マッドナースの搾精実験〜敵組織の悪のナースに捕まった貴方は一日中連続搾精で快楽実験のモルモットにされる〜","mediaStreamUrl":"https://raw.kiko-play-niptan.one/media/stream/daily/2022-10-15/RJ418548/1.%E6%9C%AC%E7%B7%A8WAV%E7%89%88%EF%BC%88%E9%AB%98%E9%9F%B3%E8%B3%AA%EF%BC%89/9.%E7%AC%AC8%E7%AB%A0%EF%BC%88%E7%99%BD%EF%BC%89%20.wav","mediaDownloadUrl":"https://raw.kiko-play-niptan.one/media/download/daily/2022-10-15/RJ418548/1.%E6%9C%AC%E7%B7%A8WAV%E7%89%88%EF%BC%88%E9%AB%98%E9%9F%B3%E8%B3%AA%EF%BC%89/9.%E7%AC%AC8%E7%AB%A0%EF%BC%88%E7%99%BD%EF%BC%89%20.wav","streamLowQualityUrl":"https://fast.kiko-play-niptan.one/media/stream/daily/2022-10-15/RJ418548/1.%E6%9C%AC%E7%B7%A8WAV%E7%89%88%EF%BC%88%E9%AB%98%E9%9F%B3%E8%B3%AA%EF%BC%89/9.%E7%AC%AC8%E7%AB%A0%EF%BC%88%E7%99%BD%EF%BC%89%20.m4a","duration":675.583333},{"type":"audio","hash":"418548/44","title":"10.第8章（黒） .wav","workTitle":"【逆レイプ】【オホ声】【連続射精】マッドナースの搾精実験〜敵組織の悪のナースに捕まった貴方は一日中連続搾精で快楽実験のモルモットにされる〜","mediaStreamUrl":"https://raw.kiko-play-niptan.one/media/stream/daily/2022-10-15/RJ418548/1.%E6%9C%AC%E7%B7%A8WAV%E7%89%88%EF%BC%88%E9%AB%98%E9%9F%B3%E8%B3%AA%EF%BC%89/10.%E7%AC%AC8%E7%AB%A0%EF%BC%88%E9%BB%92%EF%BC%89%20.wav","mediaDownloadUrl":"https://raw.kiko-play-niptan.one/media/download/daily/2022-10-15/RJ418548/1.%E6%9C%AC%E7%B7%A8WAV%E7%89%88%EF%BC%88%E9%AB%98%E9%9F%B3%E8%B3%AA%EF%BC%89/10.%E7%AC%AC8%E7%AB%A0%EF%BC%88%E9%BB%92%EF%BC%89%20.wav","streamLowQualityUrl":"https://fast.kiko-play-niptan.one/media/stream/daily/2022-10-15/RJ418548/1.%E6%9C%AC%E7%B7%A8WAV%E7%89%88%EF%BC%88%E9%AB%98%E9%9F%B3%E8%B3%AA%EF%BC%89/10.%E7%AC%AC8%E7%AB%A0%EF%BC%88%E9%BB%92%EF%BC%89%20.m4a","duration":824.903107},{"type":"audio","hash":"418548/48","title":"11.第9章 .wav","workTitle":"【逆レイプ】【オホ声】【連続射精】マッドナースの搾精実験〜敵組織の悪のナースに捕まった貴方は一日中連続搾精で快楽実験のモルモットにされる〜","mediaStreamUrl":"https://raw.kiko-play-niptan.one/media/stream/daily/2022-10-15/RJ418548/1.%E6%9C%AC%E7%B7%A8WAV%E7%89%88%EF%BC%88%E9%AB%98%E9%9F%B3%E8%B3%AA%EF%BC%89/11.%E7%AC%AC9%E7%AB%A0%20.wav","mediaDownloadUrl":"https://raw.kiko-play-niptan.one/media/download/daily/2022-10-15/RJ418548/1.%E6%9C%AC%E7%B7%A8WAV%E7%89%88%EF%BC%88%E9%AB%98%E9%9F%B3%E8%B3%AA%EF%BC%89/11.%E7%AC%AC9%E7%AB%A0%20.wav","streamLowQualityUrl":"https://fast.kiko-play-niptan.one/media/stream/daily/2022-10-15/RJ418548/1.%E6%9C%AC%E7%B7%A8WAV%E7%89%88%EF%BC%88%E9%AB%98%E9%9F%B3%E8%B3%AA%EF%BC%89/11.%E7%AC%AC9%E7%AB%A0%20.m4a","duration":898},{"type":"audio","hash":"418548/52","title":"12.第10章 .wav","workTitle":"【逆レイプ】【オホ声】【連続射精】マッドナースの搾精実験〜敵組織の悪のナースに捕まった貴方は一日中連続搾精で快楽実験のモルモットにされる〜","mediaStreamUrl":"https://raw.kiko-play-niptan.one/media/stream/daily/2022-10-15/RJ418548/1.%E6%9C%AC%E7%B7%A8WAV%E7%89%88%EF%BC%88%E9%AB%98%E9%9F%B3%E8%B3%AA%EF%BC%89/12.%E7%AC%AC10%E7%AB%A0%20.wav","mediaDownloadUrl":"https://raw.kiko-play-niptan.one/media/download/daily/2022-10-15/RJ418548/1.%E6%9C%AC%E7%B7%A8WAV%E7%89%88%EF%BC%88%E9%AB%98%E9%9F%B3%E8%B3%AA%EF%BC%89/12.%E7%AC%AC10%E7%AB%A0%20.wav","streamLowQualityUrl":"https://fast.kiko-play-niptan.one/media/stream/daily/2022-10-15/RJ418548/1.%E6%9C%AC%E7%B7%A8WAV%E7%89%88%EF%BC%88%E9%AB%98%E9%9F%B3%E8%B3%AA%EF%BC%89/12.%E7%AC%AC10%E7%AB%A0%20.m4a","duration":1041.958322}]},{"type":"image","hash":"418548/24","title":"5.高画質メインイラスト.jpg","workTitle":"【逆レイプ】【オホ声】【連続射精】マッドナースの搾精実験〜敵組織の悪のナースに捕まった貴方は一日中連続搾精で快楽実験のモルモットにされる〜","mediaStreamUrl":"https://raw.kiko-play-niptan.one/media/stream/daily/2022-10-15/RJ418548/5.%E9%AB%98%E7%94%BB%E8%B3%AA%E3%83%A1%E3%82%A4%E3%83%B3%E3%82%A4%E3%83%A9%E3%82%B9%E3%83%88.jpg","mediaDownloadUrl":"https://raw.kiko-play-niptan.one/media/download/daily/2022-10-15/RJ418548/5.%E9%AB%98%E7%94%BB%E8%B3%AA%E3%83%A1%E3%82%A4%E3%83%B3%E3%82%A4%E3%83%A9%E3%82%B9%E3%83%88.jpg"}]